stackit/auditlog/__init__.py
stackit/auditlog/api/__init__.py
stackit/auditlog/api/default_api.py
stackit/auditlog/api_client.py
stackit/auditlog/api_response.py
stackit/auditlog/configuration.py
stackit/auditlog/exceptions.py
stackit/auditlog/models/__init__.py
stackit/auditlog/models/audit_log_entry_context_response.py
stackit/auditlog/models/audit_log_entry_initiator_response.py
stackit/auditlog/models/audit_log_entry_request_response.py
stackit/auditlog/models/audit_log_entry_response.py
stackit/auditlog/models/audit_log_entry_service_account_delegation_info_response.py
stackit/auditlog/models/error_response.py
stackit/auditlog/models/gateway_error_response.py
stackit/auditlog/models/list_audit_log_entries_response.py
stackit/auditlog/models/service_account_delegation_info_principal_response.py
stackit/auditlog/py.typed
stackit/auditlog/rest.py
stackit_auditlog-0.1.1.dist-info/METADATA
stackit_auditlog-0.1.1.dist-info/WHEEL
stackit_auditlog-0.1.1.dist-info/licenses/LICENSE.md
stackit_auditlog-0.1.1.dist-info/licenses/NOTICE.txt
stackit_auditlog-0.1.1.dist-info/RECORD
